pre_commit_hooks_g/__init__.py
pre_commit_hooks_g/g-hooks/check-missing-items.vi
pre_commit_hooks_g/g-hooks/discard-no-changes.vi
pre_commit_hooks_g/g-hooks/g-hooks.lvlib
pre_commit_hooks_g/g-hooks/remove-mutation-history.vi
pre_commit_hooks_g/g-hooks/separate-compiled-code.vi
pre_commit_hooks_g/g-hooks/utils-exec-cmd.vi
pre_commit_hooks_g/g-hooks/utils-getbookmarks.vi
pre_commit_hooks_g/g-hooks/vi-broken.vi
pre_commit_hooks_g/g-hooks/vi-description.vi
pre_commit_hooks_g/g-hooks/vi-version.vi
pre_commit_hooks_g/g-hooks/yellow.llb
pre_commit_hooks_g/g-hooks/yellow.vi
pre_commit_hooks_g/hooks-wrapper/cli-wrapper/CLI-wrapper.lvclass
pre_commit_hooks_g/hooks-wrapper/cli-wrapper/exit-cli.vi
pre_commit_hooks_g/hooks-wrapper/cli-wrapper/open-cli.vi
pre_commit_hooks_g/hooks-wrapper/cli-wrapper/writeline-cli.vi
pre_commit_hooks_g/hooks-wrapper/consolidate-errors.vi
pre_commit_hooks_g/hooks-wrapper/hook-data.ctl
pre_commit_hooks_g/hooks-wrapper/hooks-wrapper.lvlib
pre_commit_hooks_g/hooks-wrapper/hooks-wrapper.vi
pre_commit_hooks_g/main.py
pre_commit_hooks_g-1.4.0.dist-info/LICENSE
pre_commit_hooks_g-1.4.0.dist-info/METADATA
pre_commit_hooks_g-1.4.0.dist-info/WHEEL
pre_commit_hooks_g-1.4.0.dist-info/entry_points.txt
pre_commit_hooks_g-1.4.0.dist-info/RECORD
