Metadata-Version: 2.1
Name: pre-commit-hooks-g
Version: 1.4.0
Summary: Pre-commit hooks for G
License: MIT
Author: Felipe P. Silva
Author-email: felipefoz@gmail.com
Requires-Python: >=3.11,<4.0
Classifier: Development Status :: 4 - Beta
Classifier: Intended Audience :: Developers
Classifier: License :: OSI Approved :: MIT License
Classifier: Operating System :: Microsoft :: Windows
Classifier: Programming Language :: Python :: 3
Classifier: Programming Language :: Python :: 3.11
Classifier: Programming Language :: Python :: 3.12
Project-URL: Bug Tracker, https://gitlab.com/felipe_public/pre-commit-hooks-g/-/issues
Project-URL: homepage, https://gitlab.com/felipe_public/pre-commit-hooks-g
Project-URL: repository, https://gitlab.com/felipe_public/pre-commit-hooks-g
